reticulum_telemetry_hub/__init__.py
reticulum_telemetry_hub/api/__init__.py
reticulum_telemetry_hub/api/models.py
reticulum_telemetry_hub/api/service.py
reticulum_telemetry_hub/api/storage.py
reticulum_telemetry_hub/api/storage_base.py
reticulum_telemetry_hub/api/storage_models.py
reticulum_telemetry_hub/atak_cot/__init__.py
reticulum_telemetry_hub/atak_cot/base.py
reticulum_telemetry_hub/atak_cot/chat.py
reticulum_telemetry_hub/atak_cot/detail.py
reticulum_telemetry_hub/atak_cot/event.py
reticulum_telemetry_hub/atak_cot/pytak_client.py
reticulum_telemetry_hub/atak_cot/tak_connector.py
reticulum_telemetry_hub/config/__init__.py
reticulum_telemetry_hub/config/constants.py
reticulum_telemetry_hub/config/manager.py
reticulum_telemetry_hub/config/models.py
reticulum_telemetry_hub/embedded_lxmd/__init__.py
reticulum_telemetry_hub/embedded_lxmd/embedded.py
reticulum_telemetry_hub/internal_api/__init__.py
reticulum_telemetry_hub/internal_api/bus.py
reticulum_telemetry_hub/internal_api/core.py
reticulum_telemetry_hub/internal_api/v1/__init__.py
reticulum_telemetry_hub/internal_api/v1/enums.py
reticulum_telemetry_hub/internal_api/v1/manifest.json
reticulum_telemetry_hub/internal_api/v1/schemas.py
reticulum_telemetry_hub/internal_api/versioning.py
reticulum_telemetry_hub/lxmf_daemon/Handlers.py
reticulum_telemetry_hub/lxmf_daemon/LXMF.py
reticulum_telemetry_hub/lxmf_daemon/LXMPeer.py
reticulum_telemetry_hub/lxmf_daemon/LXMRouter.py
reticulum_telemetry_hub/lxmf_daemon/LXMessage.py
reticulum_telemetry_hub/lxmf_daemon/LXStamper.py
reticulum_telemetry_hub/lxmf_daemon/__init__.py
reticulum_telemetry_hub/lxmf_daemon/_version.py
reticulum_telemetry_hub/lxmf_daemon/lxmd.py
reticulum_telemetry_hub/lxmf_telemetry/__init__.py
reticulum_telemetry_hub/lxmf_telemetry/model/fields/field_telemetry_stream.py
reticulum_telemetry_hub/lxmf_telemetry/model/persistance/__init__.py
reticulum_telemetry_hub/lxmf_telemetry/model/persistance/appearance.py
reticulumtelemetryhub-0.143.0.dist-info/METADATA
reticulumtelemetryhub-0.143.0.dist-info/WHEEL
reticulumtelemetryhub-0.143.0.dist-info/licenses/LICENSE
reticulumtelemetryhub-0.143.0.dist-info/RECORD
