Metadata-Version: 2.4
Name: ReticulumTelemetryHub
Version: 0.143.0
Summary: Reticulum-Telemetry-Hub (RTH) manages a complete TCP node across a Reticulum-based network, enabling communication and data sharing between clients like Sideband or Meshchat.
License-File: LICENSE
Author: naman108, corvo
Requires-Python: >=3.10,<4.0
Classifier: Programming Language :: Python :: 3
Classifier: Programming Language :: Python :: 3.10
Classifier: Programming Language :: Python :: 3.11
Classifier: Programming Language :: Python :: 3.12
Classifier: Programming Language :: Python :: 3.13
Classifier: Programming Language :: Python :: 3.14
Requires-Dist: aiohttp (>=3.10.10,<4.0.0)
Requires-Dist: cryptography (>=46.0.2,<47.0.0)
Requires-Dist: fastapi (>=0.115.0,<0.116.0)
Requires-Dist: gpsdclient (>=1.3.2,<2.0.0)
Requires-Dist: httpx (>=0.27.0,<0.28.0)
Requires-Dist: lxmf (>=0.9.4,<0.10.0)
Requires-Dist: msgpack (>=1.0.8,<2.0.0)
Requires-Dist: pydantic (>=2.8.2,<3.0.0)
Requires-Dist: pynacl (>=1.5.0,<2.0.0)
Requires-Dist: pytak (>=7.0.2,<8.0.0)
Requires-Dist: pytest (>=8.3.2,<9.0.0)
Requires-Dist: pytest-cov (>=6.1,<7.0)
Requires-Dist: python-dotenv (>=1.0.1,<2.0.0)
Requires-Dist: python-multipart (>=0.0.20,<0.0.21)
Requires-Dist: qrcode (>=7.4.2,<8.0.0)
Requires-Dist: rns (>=1.1.1,<2.0.0)
Requires-Dist: sqlalchemy (>=2.0.32,<3.0.0)
Requires-Dist: uvicorn (>=0.30.0,<0.31.0)
